robocode_tank_royale/bot_api/__init__.py
robocode_tank_royale/bot_api/base_bot.py
robocode_tank_royale/bot_api/base_bot_abc.py
robocode_tank_royale/bot_api/bot.py
robocode_tank_royale/bot_api/bot_abc.py
robocode_tank_royale/bot_api/bot_exception.py
robocode_tank_royale/bot_api/bot_info.py
robocode_tank_royale/bot_api/bot_results.py
robocode_tank_royale/bot_api/bot_state.py
robocode_tank_royale/bot_api/bullet_state.py
robocode_tank_royale/bot_api/color.py
robocode_tank_royale/bot_api/constants.py
robocode_tank_royale/bot_api/default_event_priority.py
robocode_tank_royale/bot_api/droid_abc.py
robocode_tank_royale/bot_api/game_setup.py
robocode_tank_royale/bot_api/game_type.py
robocode_tank_royale/bot_api/initial_position.py
robocode_tank_royale/bot_api/py.typed
robocode_tank_royale/bot_api/events/__init__.py
robocode_tank_royale/bot_api/events/bot_death_event.py
robocode_tank_royale/bot_api/events/bot_event.py
robocode_tank_royale/bot_api/events/bullet_fired_event.py
robocode_tank_royale/bot_api/events/bullet_hit_bot_event.py
robocode_tank_royale/bot_api/events/bullet_hit_bullet_event.py
robocode_tank_royale/bot_api/events/bullet_hit_wall_event.py
robocode_tank_royale/bot_api/events/condition.py
robocode_tank_royale/bot_api/events/connected_event.py
robocode_tank_royale/bot_api/events/connection_error_event.py
robocode_tank_royale/bot_api/events/connection_event.py
robocode_tank_royale/bot_api/events/custom_event.py
robocode_tank_royale/bot_api/events/death_event.py
robocode_tank_royale/bot_api/events/disconnected_event.py
robocode_tank_royale/bot_api/events/event_abc.py
robocode_tank_royale/bot_api/events/game_ended_event.py
robocode_tank_royale/bot_api/events/game_started_event.py
robocode_tank_royale/bot_api/events/hit_bot_event.py
robocode_tank_royale/bot_api/events/hit_by_bullet_event.py
robocode_tank_royale/bot_api/events/hit_wall_event.py
robocode_tank_royale/bot_api/events/round_ended_event.py
robocode_tank_royale/bot_api/events/round_started_event.py
robocode_tank_royale-0.34.2.dist-info/METADATA
robocode_tank_royale-0.34.2.dist-info/WHEEL
robocode_tank_royale-0.34.2.dist-info/top_level.txt
robocode_tank_royale-0.34.2.dist-info/RECORD
