Metadata-Version: 2.4
Name: robocode-tank-royale
Version: 0.34.2
Summary: Python Bot API for Robocode Tank Royale
Home-page: https://robocode-dev.github.io/tank-royale
Maintainer: Yang Li, Flemming N. Larsen
License-Expression: Apache-2.0
Project-URL: Homepage, https://robocode-dev.github.io/tank-royale
Classifier: Development Status :: 4 - Beta
Classifier: Intended Audience :: Developers
Classifier: Intended Audience :: Education
Classifier: Programming Language :: Python :: 3.10
Classifier: Topic :: Games/Entertainment
Classifier: Topic :: Education
Classifier: Topic :: Software Development :: Libraries :: Python Modules
Classifier: Operating System :: OS Independent
Classifier: Environment :: Console
Requires-Python: >=3.10
Requires-Dist: pip>=24
Requires-Dist: PyYAML>=6
Requires-Dist: setuptools>=77
Requires-Dist: pycountry>=24
Requires-Dist: websockets>=15
Requires-Dist: mypy
Dynamic: home-page
Dynamic: requires-dist
Dynamic: requires-python
